README.txt
bootstrap.py
buildout.cfg
setup.py
docs/HISTORY.txt
docs/LICENSE.GPL
docs/LICENSE.txt
src/collective/__init__.py
src/collective.annotationbrowser.egg-info/PKG-INFO
src/collective.annotationbrowser.egg-info/SOURCES.txt
src/collective.annotationbrowser.egg-info/dependency_links.txt
src/collective.annotationbrowser.egg-info/entry_points.txt
src/collective.annotationbrowser.egg-info/namespace_packages.txt
src/collective.annotationbrowser.egg-info/not-zip-safe
src/collective.annotationbrowser.egg-info/requires.txt
src/collective.annotationbrowser.egg-info/top_level.txt
src/collective/annotationbrowser/README.txt
src/collective/annotationbrowser/__init__.py
src/collective/annotationbrowser/configure.zcml
src/collective/annotationbrowser/testing.py
src/collective/annotationbrowser/utils.py
src/collective/annotationbrowser/browser/__init__.py
src/collective/annotationbrowser/browser/configure.zcml
src/collective/annotationbrowser/browser/edit.pt
src/collective/annotationbrowser/browser/interfaces.py
src/collective/annotationbrowser/browser/view.pt
src/collective/annotationbrowser/browser/view.py
src/collective/annotationbrowser/tests/__init__.py
src/collective/annotationbrowser/tests/tests.py