Metadata-Version: 1.0
Name: collective.annotationbrowser
Version: 0.1
Summary: Browser/editor for Zope annotations
Home-page: http://plone.org
Author: Radim Novotny
Author-email: novotny.radim@gmail.com
License: GPL
Keywords: plone zope annotations
Platform: UNKNOWN
Classifier: Framework :: Plone
Classifier: Programming Language :: Python
Classifier: Topic :: Software Development :: Libraries :: Python Modules
